[
  {
    "name": "Jared Triolo",
    "recentHits": [
      2,
      4,
      2,
      0,
      3,
      0,
      2,
      0,
      0,
      1
    ],
    "Continue 2 Hit Streak %": 72.22222222222221,
    "2 hit streak occcurences": 18,
    "Continue 3 Hit Streak %": 84.61538461538461,
    "3 hit streak occcurences": 13,
    "url": "https://www.espn.com/mlb/player/gamelog/_/id/42933",
    "Team": "pit"
  },
  {
    "name": "Jordan Walker",
    "recentHits": [
      1,
      1,
      1,
      1,
      1,
      1,
      1,
      1,
      1,
      2
    ],
    "Continue 2 Hit Streak %": 78.68852459016394,
    "2 hit streak occcurences": 61,
    "Continue 3 Hit Streak %": 80.85106382978722,
    "3 hit streak occcurences": 47,
    "url": "https://www.espn.com/mlb/player/gamelog/_/id/4684778",
    "Team": "stl"
  },
  {
    "name": "Nolan Schanuel",
    "recentHits": [
      1,
      1,
      1,
      1,
      0,
      1,
      3,
      0,
      2,
      2
    ],
    "Continue 2 Hit Streak %": 66.66666666666666,
    "2 hit streak occcurences": 15,
    "Continue 3 Hit Streak %": 80,
    "3 hit streak occcurences": 10,
    "url": "https://www.espn.com/mlb/player/gamelog/_/id/4739755",
    "Team": "laa"
  },
  {
    "name": "William Contreras",
    "recentHits": [
      2,
      2,
      1,
      1,
      2,
      1,
      1,
      1,
      2,
      1
    ],
    "Continue 2 Hit Streak %": 72.85714285714285,
    "2 hit streak occcurences": 70,
    "Continue 3 Hit Streak %": 76,
    "3 hit streak occcurences": 50,
    "url": "https://www.espn.com/mlb/player/gamelog/_/id/39895",
    "Team": "mil"
  },
  {
    "name": "Randal Grichuk",
    "recentHits": [
      1,
      1,
      1,
      1,
      2,
      0,
      2,
      1,
      0,
      1
    ],
    "Continue 2 Hit Streak %": 68,
    "2 hit streak occcurences": 50,
    "Continue 3 Hit Streak %": 75.75757575757575,
    "3 hit streak occcurences": 33,
    "url": "https://www.espn.com/mlb/player/gamelog/_/id/31399",
    "Team": "laa"
  },
  {
    "name": "Bryan De La Cruz",
    "recentHits": [
      1,
      2,
      1,
      2,
      1,
      1,
      0,
      1,
      0,
      0
    ],
    "Continue 2 Hit Streak %": 68.33333333333333,
    "2 hit streak occcurences": 60,
    "Continue 3 Hit Streak %": 75,
    "3 hit streak occcurences": 40,
    "url": "https://www.espn.com/mlb/player/gamelog/_/id/40787",
    "Team": "mia"
  },
  {
    "name": "Bo Bichette",
    "recentHits": [
      2,
      2,
      1,
      0,
      2,
      2,
      0,
      1,
      0,
      2
    ],
    "Continue 2 Hit Streak %": 73.91304347826086,
    "2 hit streak occcurences": 69,
    "Continue 3 Hit Streak %": 74.50980392156863,
    "3 hit streak occcurences": 51,
    "url": "https://www.espn.com/mlb/player/gamelog/_/id/38904",
    "Team": "tor"
  },
  {
    "name": "Ronald Acuna Jr.",
    "recentHits": [
      1,
      2,
      1,
      1,
      3,
      1,
      2,
      3,
      1,
      0
    ],
    "Continue 2 Hit Streak %": 73.33333333333333,
    "2 hit streak occcurences": 90,
    "Continue 3 Hit Streak %": 73.84615384615385,
    "3 hit streak occcurences": 65,
    "url": "https://www.espn.com/mlb/player/gamelog/_/id/36185",
    "Team": "atl"
  },
  {
    "name": "Austin Riley",
    "recentHits": [
      1,
      2,
      3,
      1,
      2,
      0,
      0,
      2,
      2,
      2
    ],
    "Continue 2 Hit Streak %": 70.51282051282051,
    "2 hit streak occcurences": 78,
    "Continue 3 Hit Streak %": 72.22222222222221,
    "3 hit streak occcurences": 54,
    "url": "https://www.espn.com/mlb/player/gamelog/_/id/34982",
    "Team": "atl"
  },
  {
    "name": "Masataka Yoshida",
    "recentHits": [
      1,
      3,
      1,
      1,
      1,
      0,
      0,
      1,
      0,
      0
    ],
    "Continue 2 Hit Streak %": 67.27272727272727,
    "2 hit streak occcurences": 55,
    "Continue 3 Hit Streak %": 72.22222222222221,
    "3 hit streak occcurences": 36,
    "url": "https://www.espn.com/mlb/player/gamelog/_/id/4872598",
    "Team": "bos"
  },
  {
    "name": "Nick Castellanos",
    "recentHits": [
      1,
      2,
      1,
      2,
      2,
      0,
      1,
      1,
      2,
      1
    ],
    "Continue 2 Hit Streak %": 61.42857142857143,
    "2 hit streak occcurences": 70,
    "Continue 3 Hit Streak %": 71.42857142857143,
    "3 hit streak occcurences": 42,
    "url": "https://www.espn.com/mlb/player/gamelog/_/id/31187",
    "Team": "phi"
  },
  {
    "name": "Willi Castro",
    "recentHits": [
      1,
      2,
      2,
      0,
      0,
      2,
      1,
      0,
      1,
      0
    ],
    "Continue 2 Hit Streak %": 51.515151515151516,
    "2 hit streak occcurences": 33,
    "Continue 3 Hit Streak %": 70.58823529411765,
    "3 hit streak occcurences": 17,
    "url": "https://www.espn.com/mlb/player/gamelog/_/id/34230",
    "Team": "min"
  },
  {
    "name": "Yordan Alvarez",
    "recentHits": [
      2,
      2,
      1,
      1,
      0,
      0,
      0,
      1,
      2,
      1
    ],
    "Continue 2 Hit Streak %": 71.42857142857143,
    "2 hit streak occcurences": 56,
    "Continue 3 Hit Streak %": 70,
    "3 hit streak occcurences": 40,
    "url": "https://www.espn.com/mlb/player/gamelog/_/id/36018",
    "Team": "hou"
  },
  {
    "name": "Eloy Jimenez",
    "recentHits": [
      1,
      2,
      1,
      2,
      0,
      2,
      1,
      1,
      1,
      1
    ],
    "Continue 2 Hit Streak %": 72.88135593220339,
    "2 hit streak occcurences": 59,
    "Continue 3 Hit Streak %": 69.76744186046511,
    "3 hit streak occcurences": 43,
    "url": "https://www.espn.com/mlb/player/gamelog/_/id/33867",
    "Team": "chw"
  },
  {
    "name": "Juan Soto",
    "recentHits": [
      1,
      3,
      1,
      3,
      0,
      1,
      2,
      3,
      1,
      1
    ],
    "Continue 2 Hit Streak %": 62.06896551724138,
    "2 hit streak occcurences": 58,
    "Continue 3 Hit Streak %": 69.44444444444444,
    "3 hit streak occcurences": 36,
    "url": "https://www.espn.com/mlb/player/gamelog/_/id/36969",
    "Team": "sdg"
  },
  {
    "name": "Xander Bogaerts",
    "recentHits": [
      2,
      2,
      1,
      0,
      3,
      2,
      3,
      2,
      2,
      2
    ],
    "Continue 2 Hit Streak %": 71.42857142857143,
    "2 hit streak occcurences": 77,
    "Continue 3 Hit Streak %": 69.0909090909091,
    "3 hit streak occcurences": 55,
    "url": "https://www.espn.com/mlb/player/gamelog/_/id/31606",
    "Team": "sdg"
  },
  {
    "name": "Ildemaro Vargas",
    "recentHits": [
      1,
      1,
      1,
      1,
      0,
      1,
      0,
      2,
      2,
      2
    ],
    "Continue 2 Hit Streak %": 61.53846153846154,
    "2 hit streak occcurences": 26,
    "Continue 3 Hit Streak %": 68.75,
    "3 hit streak occcurences": 16,
    "url": "https://www.espn.com/mlb/player/gamelog/_/id/32985",
    "Team": "was"
  },
  {
    "name": "Esteury Ruiz",
    "recentHits": [
      2,
      2,
      1,
      0,
      1,
      1,
      0,
      1,
      0,
      0
    ],
    "Continue 2 Hit Streak %": 67.3076923076923,
    "2 hit streak occcurences": 52,
    "Continue 3 Hit Streak %": 68.57142857142857,
    "3 hit streak occcurences": 35,
    "url": "https://www.espn.com/mlb/player/gamelog/_/id/39680",
    "Team": "oak"
  },
  {
    "name": "Brandon Nimmo",
    "recentHits": [
      1,
      1,
      1,
      3,
      3,
      1,
      2,
      0,
      1,
      2
    ],
    "Continue 2 Hit Streak %": 69.23076923076923,
    "2 hit streak occcurences": 65,
    "Continue 3 Hit Streak %": 68.18181818181817,
    "3 hit streak occcurences": 44,
    "url": "https://www.espn.com/mlb/player/gamelog/_/id/32159",
    "Team": "nym"
  },
  {
    "name": "Harold Ramirez",
    "recentHits": [
      3,
      2,
      2,
      1,
      0,
      0,
      0,
      2,
      1,
      2
    ],
    "Continue 2 Hit Streak %": 60.86956521739131,
    "2 hit streak occcurences": 46,
    "Continue 3 Hit Streak %": 67.85714285714286,
    "3 hit streak occcurences": 28,
    "url": "https://www.espn.com/mlb/player/gamelog/_/id/33259",
    "Team": "tam"
  },
  {
    "name": "Christian Walker",
    "recentHits": [
      1,
      1,
      1,
      3,
      0,
      0,
      2,
      0,
      0,
      0
    ],
    "Continue 2 Hit Streak %": 58.620689655172406,
    "2 hit streak occcurences": 58,
    "Continue 3 Hit Streak %": 67.64705882352942,
    "3 hit streak occcurences": 34,
    "url": "https://www.espn.com/mlb/player/gamelog/_/id/32758",
    "Team": "ari"
  },
  {
    "name": "DJ LeMahieu",
    "recentHits": [
      2,
      1,
      1,
      0,
      1,
      1,
      1,
      2,
      3,
      1
    ],
    "Continue 2 Hit Streak %": 71.875,
    "2 hit streak occcurences": 64,
    "Continue 3 Hit Streak %": 67.3913043478261,
    "3 hit streak occcurences": 46,
    "url": "https://www.espn.com/mlb/player/gamelog/_/id/30765",
    "Team": "nyy"
  },
  {
    "name": "Curtis Mead",
    "recentHits": [
      1,
      1,
      2,
      0,
      1,
      1,
      1,
      2,
      0,
      1
    ],
    "Continue 2 Hit Streak %": 75,
    "2 hit streak occcurences": 8,
    "Continue 3 Hit Streak %": 66.66666666666666,
    "3 hit streak occcurences": 6,
    "url": "https://www.espn.com/mlb/player/gamelog/_/id/42360",
    "Team": "tam"
  },
  {
    "name": "Jorge Soler",
    "recentHits": [
      3,
      1,
      1,
      2,
      1,
      0,
      2,
      0,
      1,
      2
    ],
    "Continue 2 Hit Streak %": 59.61538461538461,
    "2 hit streak occcurences": 52,
    "Continue 3 Hit Streak %": 66.66666666666666,
    "3 hit streak occcurences": 30,
    "url": "https://www.espn.com/mlb/player/gamelog/_/id/32558",
    "Team": "mia"
  },
  {
    "name": "JJ Bleday",
    "recentHits": [
      1,
      1,
      1,
      0,
      1,
      1,
      0,
      0,
      0,
      1
    ],
    "Continue 2 Hit Streak %": 47.368421052631575,
    "2 hit streak occcurences": 19,
    "Continue 3 Hit Streak %": 66.66666666666666,
    "3 hit streak occcurences": 9,
    "url": "https://www.espn.com/mlb/player/gamelog/_/id/42410",
    "Team": "oak"
  },
  {
    "name": "Seiya Suzuki",
    "recentHits": [
      2,
      1,
      3,
      0,
      1,
      3,
      0,
      1,
      1,
      0
    ],
    "Continue 2 Hit Streak %": 68.33333333333333,
    "2 hit streak occcurences": 60,
    "Continue 3 Hit Streak %": 65.85365853658537,
    "3 hit streak occcurences": 41,
    "url": "https://www.espn.com/mlb/player/gamelog/_/id/4142424",
    "Team": "chc"
  },
  {
    "name": "Adolis Garcia",
    "recentHits": [
      1,
      1,
      2,
      0,
      1,
      1,
      0,
      0,
      0,
      1
    ],
    "Continue 2 Hit Streak %": 60.416666666666664,
    "2 hit streak occcurences": 48,
    "Continue 3 Hit Streak %": 65.51724137931035,
    "3 hit streak occcurences": 29,
    "url": "https://www.espn.com/mlb/player/gamelog/_/id/35537",
    "Team": "tex"
  },
  {
    "name": "Fernando Tatis Jr.",
    "recentHits": [
      2,
      2,
      1,
      1,
      0,
      1,
      2,
      1,
      1,
      2
    ],
    "Continue 2 Hit Streak %": 69.6969696969697,
    "2 hit streak occcurences": 66,
    "Continue 3 Hit Streak %": 65.21739130434783,
    "3 hit streak occcurences": 46,
    "url": "https://www.espn.com/mlb/player/gamelog/_/id/35983",
    "Team": "sdg"
  },
  {
    "name": "Orlando Arcia",
    "recentHits": [
      2,
      2,
      3,
      0,
      0,
      0,
      0,
      0,
      2,
      0
    ],
    "Continue 2 Hit Streak %": 63.26530612244898,
    "2 hit streak occcurences": 49,
    "Continue 3 Hit Streak %": 64.51612903225806,
    "3 hit streak occcurences": 31,
    "url": "https://www.espn.com/mlb/player/gamelog/_/id/32530",
    "Team": "atl"
  },
  {
    "name": "George Springer",
    "recentHits": [
      1,
      1,
      2,
      1,
      2,
      2,
      1,
      0,
      0,
      0
    ],
    "Continue 2 Hit Streak %": 70.76923076923077,
    "2 hit streak occcurences": 65,
    "Continue 3 Hit Streak %": 64.44444444444444,
    "3 hit streak occcurences": 45,
    "url": "https://www.espn.com/mlb/player/gamelog/_/id/32078",
    "Team": "tor"
  },
  {
    "name": "Wander Franco",
    "recentHits": [
      1,
      2,
      2,
      3,
      1,
      3,
      3,
      0,
      1,
      1
    ],
    "Continue 2 Hit Streak %": 68,
    "2 hit streak occcurences": 50,
    "Continue 3 Hit Streak %": 63.63636363636363,
    "3 hit streak occcurences": 33,
    "url": "https://www.espn.com/mlb/player/gamelog/_/id/40929",
    "Team": "tam"
  },
  {
    "name": "Bryce Harper",
    "recentHits": [
      1,
      2,
      1,
      2,
      0,
      1,
      1,
      1,
      0,
      0
    ],
    "Continue 2 Hit Streak %": 67.79661016949152,
    "2 hit streak occcurences": 59,
    "Continue 3 Hit Streak %": 62.5,
    "3 hit streak occcurences": 40,
    "url": "https://www.espn.com/mlb/player/gamelog/_/id/30951",
    "Team": "phi"
  },
  {
    "name": "Ji Hwan Bae",
    "recentHits": [
      2,
      1,
      1,
      0,
      0,
      1,
      0,
      1,
      1,
      1
    ],
    "Continue 2 Hit Streak %": 57.14285714285714,
    "2 hit streak occcurences": 28,
    "Continue 3 Hit Streak %": 62.5,
    "3 hit streak occcurences": 16,
    "url": "https://www.espn.com/mlb/player/gamelog/_/id/40896",
    "Team": "pit"
  },
  {
    "name": "Kevin Kiermaier",
    "recentHits": [
      1,
      1,
      1,
      2,
      1,
      0,
      0,
      0,
      0,
      0
    ],
    "Continue 2 Hit Streak %": 56.41025641025641,
    "2 hit streak occcurences": 39,
    "Continue 3 Hit Streak %": 61.904761904761905,
    "3 hit streak occcurences": 21,
    "url": "https://www.espn.com/mlb/player/gamelog/_/id/31446",
    "Team": "tor"
  },
  {
    "name": "Carlos Santana",
    "recentHits": [
      2,
      1,
      3,
      0,
      1,
      0,
      1,
      0,
      2,
      2
    ],
    "Continue 2 Hit Streak %": 54.166666666666664,
    "2 hit streak occcurences": 48,
    "Continue 3 Hit Streak %": 61.53846153846154,
    "3 hit streak occcurences": 26,
    "url": "https://www.espn.com/mlb/player/gamelog/_/id/30280",
    "Team": "mil"
  },
  {
    "name": "Jorge Polanco",
    "recentHits": [
      1,
      2,
      1,
      1,
      0,
      1,
      2,
      1,
      1,
      1
    ],
    "Continue 2 Hit Streak %": 64.1025641025641,
    "2 hit streak occcurences": 39,
    "Continue 3 Hit Streak %": 60,
    "3 hit streak occcurences": 25,
    "url": "https://www.espn.com/mlb/player/gamelog/_/id/32525",
    "Team": "min"
  },
  {
    "name": "Jon Berti",
    "recentHits": [
      2,
      1,
      2,
      2,
      1,
      1,
      0,
      0,
      0,
      1
    ],
    "Continue 2 Hit Streak %": 58.97435897435898,
    "2 hit streak occcurences": 39,
    "Continue 3 Hit Streak %": 59.09090909090909,
    "3 hit streak occcurences": 22,
    "url": "https://www.espn.com/mlb/player/gamelog/_/id/32273",
    "Team": "mia"
  },
  {
    "name": "J.T. Realmuto",
    "recentHits": [
      2,
      2,
      1,
      1,
      1,
      1,
      0,
      0,
      2,
      1
    ],
    "Continue 2 Hit Streak %": 61.224489795918366,
    "2 hit streak occcurences": 49,
    "Continue 3 Hit Streak %": 58.620689655172406,
    "3 hit streak occcurences": 29,
    "url": "https://www.espn.com/mlb/player/gamelog/_/id/32177",
    "Team": "phi"
  },
  {
    "name": "Corey Seager",
    "recentHits": [
      1,
      1,
      1,
      2,
      1,
      1,
      0,
      0,
      0,
      1
    ],
    "Continue 2 Hit Streak %": 67.74193548387096,
    "2 hit streak occcurences": 62,
    "Continue 3 Hit Streak %": 58.536585365853654,
    "3 hit streak occcurences": 41,
    "url": "https://www.espn.com/mlb/player/gamelog/_/id/32691",
    "Team": "tex"
  },
  {
    "name": "Adley Rutschman",
    "recentHits": [
      2,
      2,
      1,
      3,
      1,
      1,
      3,
      1,
      0,
      0
    ],
    "Continue 2 Hit Streak %": 65.625,
    "2 hit streak occcurences": 64,
    "Continue 3 Hit Streak %": 58.536585365853654,
    "3 hit streak occcurences": 41,
    "url": "https://www.espn.com/mlb/player/gamelog/_/id/42178",
    "Team": "bal"
  },
  {
    "name": "Christian Yelich",
    "recentHits": [
      1,
      2,
      3,
      0,
      1,
      1,
      0,
      0,
      0,
      1
    ],
    "Continue 2 Hit Streak %": 62.5,
    "2 hit streak occcurences": 64,
    "Continue 3 Hit Streak %": 57.49999999999999,
    "3 hit streak occcurences": 40,
    "url": "https://www.espn.com/mlb/player/gamelog/_/id/31283",
    "Team": "mil"
  },
  {
    "name": "Mitch Garver",
    "recentHits": [
      3,
      1,
      2,
      1,
      1,
      0,
      0,
      0,
      1,
      0
    ],
    "Continue 2 Hit Streak %": 61.111111111111114,
    "2 hit streak occcurences": 36,
    "Continue 3 Hit Streak %": 57.14285714285714,
    "3 hit streak occcurences": 21,
    "url": "https://www.espn.com/mlb/player/gamelog/_/id/33667",
    "Team": "tex"
  },
  {
    "name": "TJ Friedl",
    "recentHits": [
      2,
      2,
      2,
      1,
      1,
      1,
      0,
      2,
      0,
      1
    ],
    "Continue 2 Hit Streak %": 62.5,
    "2 hit streak occcurences": 48,
    "Continue 3 Hit Streak %": 55.172413793103445,
    "3 hit streak occcurences": 29,
    "url": "https://www.espn.com/mlb/player/gamelog/_/id/36020",
    "Team": "cin"
  },
  {
    "name": "Josh Lowe",
    "recentHits": [
      1,
      3,
      1,
      1,
      1,
      1,
      1,
      0,
      0,
      1
    ],
    "Continue 2 Hit Streak %": 61.224489795918366,
    "2 hit streak occcurences": 49,
    "Continue 3 Hit Streak %": 55.172413793103445,
    "3 hit streak occcurences": 29,
    "url": "https://www.espn.com/mlb/player/gamelog/_/id/40557",
    "Team": "tam"
  },
  {
    "name": "Johan Rojas",
    "recentHits": [
      1,
      1,
      1,
      0,
      1,
      1,
      1,
      2,
      2,
      0
    ],
    "Continue 2 Hit Streak %": 68.75,
    "2 hit streak occcurences": 16,
    "Continue 3 Hit Streak %": 54.54545454545454,
    "3 hit streak occcurences": 11,
    "url": "https://www.espn.com/mlb/player/gamelog/_/id/42829",
    "Team": "phi"
  },
  {
    "name": "Kyle Isbel",
    "recentHits": [
      1,
      1,
      1,
      0,
      1,
      0,
      0,
      2,
      1,
      0
    ],
    "Continue 2 Hit Streak %": 45.83333333333333,
    "2 hit streak occcurences": 24,
    "Continue 3 Hit Streak %": 54.54545454545454,
    "3 hit streak occcurences": 11,
    "url": "https://www.espn.com/mlb/player/gamelog/_/id/41263",
    "Team": "kan"
  },
  {
    "name": "Dansby Swanson",
    "recentHits": [
      1,
      1,
      1,
      2,
      0,
      2,
      1,
      0,
      0,
      1
    ],
    "Continue 2 Hit Streak %": 52.94117647058824,
    "2 hit streak occcurences": 51,
    "Continue 3 Hit Streak %": 51.85185185185185,
    "3 hit streak occcurences": 27,
    "url": "https://www.espn.com/mlb/player/gamelog/_/id/34895",
    "Team": "chc"
  },
  {
    "name": "Manny Machado",
    "recentHits": [
      2,
      1,
      4,
      0,
      0,
      2,
      0,
      1,
      2,
      0
    ],
    "Continue 2 Hit Streak %": 59.61538461538461,
    "2 hit streak occcurences": 52,
    "Continue 3 Hit Streak %": 51.61290322580645,
    "3 hit streak occcurences": 31,
    "url": "https://www.espn.com/mlb/player/gamelog/_/id/31097",
    "Team": "sdg"
  },
  {
    "name": "Noelvi Marte",
    "recentHits": [
      1,
      1,
      1,
      1,
      1,
      3,
      1,
      2,
      0,
      0
    ],
    "Continue 2 Hit Streak %": 64.28571428571429,
    "2 hit streak occcurences": 14,
    "Continue 3 Hit Streak %": 50,
    "3 hit streak occcurences": 8,
    "url": "https://www.espn.com/mlb/player/gamelog/_/id/41307",
    "Team": "cin"
  },
  {
    "name": "Henry Davis",
    "recentHits": [
      2,
      1,
      1,
      1,
      0,
      0,
      0,
      0,
      0,
      0
    ],
    "Continue 2 Hit Streak %": 58.82352941176471,
    "2 hit streak occcurences": 17,
    "Continue 3 Hit Streak %": 50,
    "3 hit streak occcurences": 10,
    "url": "https://www.espn.com/mlb/player/gamelog/_/id/4418683",
    "Team": "pit"
  },
  {
    "name": "Santiago Espinal",
    "recentHits": [
      1,
      1,
      1,
      0,
      2,
      1,
      1,
      0,
      1,
      1
    ],
    "Continue 2 Hit Streak %": 58.333333333333336,
    "2 hit streak occcurences": 24,
    "Continue 3 Hit Streak %": 50,
    "3 hit streak occcurences": 14,
    "url": "https://www.espn.com/mlb/player/gamelog/_/id/39924",
    "Team": "tor"
  },
  {
    "name": "Luis Garcia",
    "recentHits": [
      3,
      1,
      2,
      2,
      3,
      0,
      0,
      2,
      2,
      0
    ],
    "Continue 2 Hit Streak %": 52.77777777777778,
    "2 hit streak occcurences": 36,
    "Continue 3 Hit Streak %": 50,
    "3 hit streak occcurences": 18,
    "url": "https://www.espn.com/mlb/player/gamelog/_/id/40459",
    "Team": "was"
  },
  {
    "name": "Patrick Wisdom",
    "recentHits": [
      1,
      1,
      1,
      0,
      1,
      0,
      1,
      0,
      0,
      0
    ],
    "Continue 2 Hit Streak %": 40,
    "2 hit streak occcurences": 15,
    "Continue 3 Hit Streak %": 50,
    "3 hit streak occcurences": 6,
    "url": "https://www.espn.com/mlb/player/gamelog/_/id/32861",
    "Team": "chc"
  },
  {
    "name": "Christian Encarnacion-Strand",
    "recentHits": [
      1,
      3,
      1,
      1,
      0,
      2,
      2,
      0,
      1,
      0
    ],
    "Continue 2 Hit Streak %": 55.00000000000001,
    "2 hit streak occcurences": 20,
    "Continue 3 Hit Streak %": 45.45454545454545,
    "3 hit streak occcurences": 11,
    "url": "https://www.espn.com/mlb/player/gamelog/_/id/5012106",
    "Team": "cin"
  },
  {
    "name": "Kyle Farmer",
    "recentHits": [
      1,
      2,
      2,
      1,
      1,
      1,
      0,
      0,
      0,
      1
    ],
    "Continue 2 Hit Streak %": 55.88235294117647,
    "2 hit streak occcurences": 34,
    "Continue 3 Hit Streak %": 44.44444444444444,
    "3 hit streak occcurences": 18,
    "url": "https://www.espn.com/mlb/player/gamelog/_/id/33287",
    "Team": "min"
  },
  {
    "name": "Luis Campusano",
    "recentHits": [
      3,
      1,
      1,
      1,
      3,
      2,
      0,
      1,
      2,
      1
    ],
    "Continue 2 Hit Streak %": 56.25,
    "2 hit streak occcurences": 16,
    "Continue 3 Hit Streak %": 37.5,
    "3 hit streak occcurences": 8,
    "url": "https://www.espn.com/mlb/player/gamelog/_/id/40521",
    "Team": "sdg"
  },
  {
    "name": "Zach McKinstry",
    "recentHits": [
      1,
      2,
      1,
      0,
      0,
      0,
      0,
      0,
      0,
      0
    ],
    "Continue 2 Hit Streak %": 50,
    "2 hit streak occcurences": 46,
    "Continue 3 Hit Streak %": 30.434782608695656,
    "3 hit streak occcurences": 23,
    "url": "https://www.espn.com/mlb/player/gamelog/_/id/38420",
    "Team": "det"
  },
  {
    "name": "Jo Adell",
    "recentHits": [
      1,
      1,
      1,
      0,
      2,
      0,
      1,
      0,
      0,
      1
    ],
    "Continue 2 Hit Streak %": 50,
    "2 hit streak occcurences": 2,
    "Continue 3 Hit Streak %": 0,
    "3 hit streak occcurences": 1,
    "url": "https://www.espn.com/mlb/player/gamelog/_/id/40854",
    "Team": "laa"
  },
  {
    "name": "Michael Stefanic",
    "recentHits": [
      3,
      1,
      1,
      2,
      2,
      2,
      0,
      0,
      0,
      0
    ],
    "Continue 2 Hit Streak %": 50,
    "2 hit streak occcurences": 4,
    "Continue 3 Hit Streak %": 0,
    "3 hit streak occcurences": 1,
    "url": "https://www.espn.com/mlb/player/gamelog/_/id/42711",
    "Team": "laa"
  }
]